plot_and_log_memory_usage/__init__.py
plot_and_log_memory_usage/log_memory_usage.py
plot_and_log_memory_usage/plot_logged_memory_usage.py
plot_and_log_memory_usage/utils.py
plot_and_log_memory_usage-0.0.1.dist-info/LICENSE
plot_and_log_memory_usage-0.0.1.dist-info/METADATA
plot_and_log_memory_usage-0.0.1.dist-info/WHEEL
plot_and_log_memory_usage-0.0.1.dist-info/entry_points.txt
plot_and_log_memory_usage-0.0.1.dist-info/top_level.txt
plot_and_log_memory_usage-0.0.1.dist-info/RECORD
