Metadata-Version: 2.1
Name: plot-and-log-memory-usage
Version: 0.0.1
Summary: Scripts for logging CPU and GPU memory usage and subsequently plotting for analysis and debugging
Home-page: https://github.com/tylerlum/plot_and_log_memory_usage
Author: Tyler Lum
Author-email: tylergwlum@gmail.com
Keywords: python,memory,usage,plot,logging
Classifier: Intended Audience :: Developers
Classifier: Operating System :: OS Independent
Classifier: Programming Language :: Python :: 3
License-File: LICENSE
Requires-Dist: matplotlib
Requires-Dist: tyro
Requires-Dist: GPUtil
Requires-Dist: psutil
Requires-Dist: pandas
